{"143371": {"commercial_dates": ["", ""], "parttime_duration": "72", "item_order": "125", "tuition_fee_types": [{"amount": "597", "currency": "USD", "unit": "credit", "target": "national"}, {"amount": "1100", "currency": "USD", "unit": "credit", "target": "international"}], "virtual_path": "public-administration.html", "fulltime_duration_period": "", "toefl_internet": "79", "title": "Public Administration", "ects_credits": "", "short_description": "The mission of the  Master Public Administration program is to prepare students for leadership roles and careers in public and nonprofit organizations.", "entropy": "394185564", "entry_level": "", "ego": "studies-cs/public/results/143371/", "components": [], "languages": {"partially": [], "fully": {"3": {"title": "English", "id": "3", "locale": "en-GB", "item_order": "120", "name": ""}}}, "premiums_out_of_date": ["listed", "sort_regular", "display_regular"], "logo": [], "cpm": "0", "parttime_duration_period": "months", "premiums_out_of_range": ["listed", "sort_regular", "display_regular", "out_of_range"], "degree_type": "", "methods": ["face2face"], "degree_formatted": "Master", "presence": "public", "inquiry_campaigns": [], "venues": {"required": [], "optional": [], "full": {"12448": {"id": "12448", "cities": {"43700": {"countries": {"82": {"title": "United States", "id": "82", "item_order": "120", "virtual_path": "united-states.html", "name": "United States"}}, "item_order": "120", "areas": {"3600": {"countries": {"82": {"item_order": "120", "virtual_path": "united-states.html", "area_presence": "yes", "title": "United States", "id": "82", "name": "United States"}}, "title": "Michigan", "id": "3600", "item_order": "120", "name": "Michigan"}}, "title": "Ypsilanti", "id": "43700", "name": "Ypsilanti"}}, "item_order": "120", "name": "Ypsilanti Campus"}}}, "rolling": "0", "cae": "", "id": "143371", "ielts": "6.5", "fce": "", "toefl_paper": "", "start_dates": [], "organisations_lineage": [{"14998": {"item_order": "121", "virtual_path": "eastern-michigan-university.html", "logo": [], "id": "14998", "name": "Eastern Michigan University", "premiums": ["listed", "sort_regular", "display_regular"], "country_id": "82"}, "15000": {"item_order": "120", "virtual_path": "college-of-arts-and-sciences.html", "logo": [], "id": "15000", "name": "College of Arts and Sciences", "premiums": ["listed", "sort_regular", "display_regular"], "country_id": "82"}}], "degree": "", "experience_years": "", "disciplines": {"101": {"title": "Public Administration", "id": "101", "parent_id": "23", "item_order": "120", "name": "Public Administration"}}, "level": "master", "lead_campaigns": [], "fulltime_duration": "", "premiums": ["listed", "sort_regular", "display_regular"], "commercial_range": ["1", "100"], "name": "Public Administration"}, "120582": {"commercial_dates": ["", ""], "parttime_duration": "", "item_order": "127", "tuition_fee_types": [{"amount": "2006", "currency": "EUR", "unit": "year", "target": "eea"}, {"amount": "15167", "currency": "EUR", "unit": "year", "target": "international"}], "virtual_path": "public-administration-and-organisational-science.html", "fulltime_duration_period": "months", "toefl_internet": "100", "title": "Public Administration and Organisational Science (Research)", "ects_credits": "120", "short_description": "New challenges for public governments flow from long-term trends such as globalisation, changing information and communication technologies, climate change, and societal fragmentation caused by migration, individualisation, and cultural pluralisation. Solid research is necessary to understand and properly react to these social transformations.", "entropy": "404922670", "entry_level": "bachelor", "ego": "studies-cs/public/results/120582/", "components": [], "languages": {"partially": [], "fully": {"3": {"title": "English", "id": "3", "locale": "en-GB", "item_order": "120", "name": ""}}}, "premiums_out_of_date": ["listed", "sort_regular", "display_regular"], "logo": [], "cpm": "0", "parttime_duration_period": "", "premiums_out_of_range": ["listed", "sort_regular", "display_regular", "out_of_range"], "degree_type": "", "methods": ["face2face"], "degree_formatted": "M.Sc.", "presence": "public", "inquiry_campaigns": [], "venues": {"required": [], "optional": [], "full": {"5230": {"id": "5230", "cities": {"69": {"countries": {"1": {"title": "Netherlands", "id": "1", "item_order": "120", "virtual_path": "netherlands.html", "name": "Netherlands"}}, "item_order": "120", "areas": {"2288": {"countries": {"1": {"item_order": "120", "virtual_path": "netherlands.html", "area_presence": "no", "title": "Netherlands", "id": "1", "name": "Netherlands"}}, "title": "Gelderland", "id": "2288", "item_order": "120", "name": "Gelderland"}}, "title": "Nijmegen", "id": "69", "name": "Nijmegen"}}, "item_order": "120", "name": "Nijmegen Campus"}}}, "rolling": "0", "cae": "193", "id": "120582", "ielts": "7", "fce": "", "toefl_paper": "", "start_dates": ["9"], "organisations_lineage": [{"4198": {"item_order": "120", "virtual_path": "nijmegen-school-of-management.html", "logo": [], "id": "4198", "name": "Nijmegen School of Management", "premiums": ["listed", "sort_regular", "display_regular"], "country_id": "1"}, "82": {"item_order": "121", "virtual_path": "radboud-university.html", "logo": {"14039": {"item_order": "120", "imgix": "//storage-prtl-co.imgix.net/mp/cdaf05b5.png", "file": "https://storage.prtl.co/mp/cdaf05b5.png", "id": "14039", "name": "New logo_resized.png", "url": "https://storage.prtl.co/mp/cdaf05b5.png"}}, "id": "82", "name": "Radboud University", "premiums": ["listed", "hide_banners", "markup", "links_website", "links_social", "links_rss", "logo", "sort_high", "display_premium", "inquiries", "gallery", "spotlight", "contact_form"], "country_id": "1"}}], "degree": "msc", "experience_years": "", "disciplines": {"103": {"title": "Organisational Behaviour", "id": "103", "parent_id": "13", "item_order": "121", "name": "Organisational Behaviour"}, "101": {"title": "Public Administration", "id": "101", "parent_id": "23", "item_order": "120", "name": "Public Administration"}}, "level": "master", "lead_campaigns": [], "fulltime_duration": "24", "premiums": ["listed", "sort_regular", "display_regular"], "commercial_range": ["1", "100"], "name": "Public Administration and Organisational Science (Research)"}, "11214": {"commercial_dates": ["", ""], "parttime_duration": "24", "item_order": "124", "tuition_fee_types": [{"amount": "6120", "currency": "GBP", "unit": "year", "target": "eea"}, {"amount": "12830", "currency": "GBP", "unit": "year", "target": "international"}], "virtual_path": "masters-in-public-administration.html", "fulltime_duration_period": "months", "toefl_internet": "", "title": "Masters in Public Administration", "ects_credits": "", "short_description": "The Masters in Public Administration programme at\u00a0University of Brighton\u00a0offers a contemporary and critical focus on major public\npolicy and management issues in the post-financial crisis era.", "entropy": "392770402", "entry_level": "bachelor", "ego": "studies-cs/public/results/11214/", "components": [], "languages": {"partially": [], "fully": {"3": {"title": "English", "id": "3", "locale": "en-GB", "item_order": "120", "name": ""}}}, "premiums_out_of_date": ["listed", "sort_regular", "display_regular"], "logo": [], "cpm": "0", "parttime_duration_period": "months", "premiums_out_of_range": ["listed", "sort_regular", "display_regular", "out_of_range"], "degree_type": "", "methods": ["face2face"], "degree_formatted": "M.B.A.", "presence": "public", "inquiry_campaigns": [], "venues": {"required": [], "optional": [], "full": {"1943": {"id": "1943", "cities": {"188": {"countries": {"30": {"title": "United Kingdom", "id": "30", "item_order": "120", "virtual_path": "united-kingdom.html", "name": "United Kingdom"}}, "item_order": "120", "areas": {"996": {"countries": {"30": {"item_order": "120", "virtual_path": "united-kingdom.html", "area_presence": "yes", "title": "United Kingdom", "id": "30", "name": "United Kingdom"}}, "title": "England", "id": "996", "item_order": "120", "name": "England"}}, "title": "Brighton", "id": "188", "name": "Brighton"}}, "item_order": "120", "name": "Brighton"}}}, "rolling": "0", "cae": "", "id": "11214", "ielts": "5.5", "fce": "", "toefl_paper": "", "start_dates": [], "organisations_lineage": [{"4932": {"item_order": "120", "virtual_path": "faculty-of-health-and-social-science.html", "logo": [], "id": "4932", "name": "Faculty of Health and Social Science", "premiums": ["listed", "sort_regular", "display_regular"], "country_id": "30"}, "524": {"item_order": "121", "virtual_path": "university-of-brighton.html", "logo": [], "id": "524", "name": "University of Brighton", "premiums": ["listed", "sort_regular", "display_regular"], "country_id": "30"}}], "degree": "mba", "experience_years": "", "disciplines": {"101": {"title": "Public Administration", "id": "101", "parent_id": "23", "item_order": "120", "name": "Public Administration"}}, "level": "master", "lead_campaigns": [], "fulltime_duration": "12", "premiums": ["listed", "sort_regular", "display_regular"], "commercial_range": ["1", "100"], "name": "Masters in Public Administration"}, "95028": {"commercial_dates": ["", ""], "parttime_duration": "", "item_order": "122", "tuition_fee_types": [], "virtual_path": "public-management.html", "fulltime_duration_period": "months", "toefl_internet": "", "title": "Public Management", "ects_credits": "", "short_description": "The degree programme requires that a dissertation/mini-dissertation must be submitted on a field of study chosen from the fields covered for the honours degree provided that the Dean may on the recommendation of the head of department concerned approve the replacement of the required dissertation by the successful completion of a prescribed number of module credits and a mini-dissertation.", "entropy": "391191962", "entry_level": "bachelor", "ego": "studies-cs/public/results/95028/", "components": [], "languages": {"partially": [], "fully": {"3": {"title": "English", "id": "3", "locale": "en-GB", "item_order": "120", "name": ""}}}, "premiums_out_of_date": ["listed", "sort_regular", "display_regular"], "logo": [], "cpm": "0", "parttime_duration_period": "", "premiums_out_of_range": ["listed", "sort_regular", "display_regular", "out_of_range"], "degree_type": "", "methods": ["face2face"], "degree_formatted": "Master", "presence": "public", "inquiry_campaigns": [], "venues": {"required": [], "optional": [], "full": {"10718": {"id": "10718", "cities": {"47248": {"countries": {"191": {"title": "South Africa", "id": "191", "item_order": "120", "virtual_path": "south-africa.html", "name": "South Africa"}}, "item_order": "120", "areas": {"3851": {"countries": {"191": {"item_order": "120", "virtual_path": "south-africa.html", "area_presence": "no", "title": "South Africa", "id": "191", "name": "South Africa"}}, "title": "Gauteng", "id": "3851", "item_order": "120", "name": "Gauteng"}}, "title": "Pretoria", "id": "47248", "name": "Pretoria"}}, "item_order": "120", "name": "Pretoria campus"}}}, "rolling": "0", "cae": "", "id": "95028", "ielts": "6", "fce": "", "toefl_paper": "", "start_dates": ["10"], "organisations_lineage": [{"13364": {"item_order": "120", "virtual_path": "university-of-pretoria.html", "logo": [], "id": "13364", "name": "University of Pretoria", "premiums": ["listed", "sort_regular", "display_regular"], "country_id": "191"}}], "degree": "", "experience_years": "", "disciplines": {"101": {"title": "Public Administration", "id": "101", "parent_id": "23", "item_order": "120", "name": "Public Administration"}}, "level": "master", "lead_campaigns": [], "fulltime_duration": "24", "premiums": ["listed", "sort_regular", "display_regular"], "commercial_range": ["1", "100"], "name": "Public Management"}, "96689": {"commercial_dates": ["", ""], "parttime_duration": "", "item_order": "129", "tuition_fee_types": [{"amount": "47668", "currency": "USD", "unit": "year", "target": "national"}, {"amount": "47668", "currency": "USD", "unit": "year", "target": "international"}], "virtual_path": "city-and-regional-planning.html", "fulltime_duration_period": "months", "toefl_internet": "", "title": "City and Regional Planning", "ects_credits": "", "short_description": "The Master of City Planning  is a hallmark of PennPlanning's cutting-edge and practical approach to educating city planners.", "entropy": "413387264", "entry_level": "bachelor", "ego": "studies-cs/public/results/96689/", "components": [], "languages": {"partially": [], "fully": {"3": {"title": "English", "id": "3", "locale": "en-GB", "item_order": "120", "name": ""}}}, "premiums_out_of_date": ["listed", "sort_regular", "display_regular"], "logo": [], "cpm": "0", "parttime_duration_period": "", "premiums_out_of_range": ["listed", "sort_regular", "display_regular", "out_of_range"], "degree_type": "", "methods": ["face2face"], "degree_formatted": "Master", "presence": "public", "inquiry_campaigns": [], "venues": {"required": [], "optional": [], "full": {"8754": {"id": "8754", "cities": {"41979": {"countries": {"82": {"title": "United States", "id": "82", "item_order": "120", "virtual_path": "united-states.html", "name": "United States"}}, "item_order": "120", "areas": {"3627": {"countries": {"82": {"item_order": "120", "virtual_path": "united-states.html", "area_presence": "yes", "title": "United States", "id": "82", "name": "United States"}}, "title": "Pennsylvania", "id": "3627", "item_order": "120", "name": "Pennsylvania"}}, "title": "Philadelphia", "id": "41979", "name": "Philadelphia"}}, "item_order": "120", "name": "Philadelphia Campus"}}}, "rolling": "0", "cae": "", "id": "96689", "ielts": "", "fce": "", "toefl_paper": "", "start_dates": [], "organisations_lineage": [{"11746": {"item_order": "120", "virtual_path": "university-of-pennsylvania.html", "logo": {"11532": {"item_order": "120", "imgix": "//storage-prtl-co.imgix.net/mp/b9b08493.jpg", "file": "https://storage.prtl.co/mp/b9b08493.jpg", "id": "11532", "name": "logo-print.jpg", "url": "https://storage.prtl.co/mp/b9b08493.jpg"}}, "id": "11746", "name": "University of Pennsylvania", "premiums": ["listed", "sort_regular", "display_regular"], "country_id": "82"}}], "degree": "", "experience_years": "", "disciplines": {"101": {"title": "Public Administration", "id": "101", "parent_id": "23", "item_order": "120", "name": "Public Administration"}}, "level": "master", "lead_campaigns": [], "fulltime_duration": "24", "premiums": ["listed", "sort_regular", "display_regular"], "commercial_range": ["1", "100"], "name": "City and Regional Planning"}, "144831": {"commercial_dates": ["", ""], "parttime_duration": "", "item_order": "126", "tuition_fee_types": [{"amount": "1486", "currency": "USD", "unit": "credit", "target": "national"}], "virtual_path": "pharmacy-administration.html", "fulltime_duration_period": "months", "toefl_internet": "100", "title": "", "ects_credits": "", "short_description": "The Master of Science Pharmacy Administration is offered by the Duquesne University.", "entropy": "398249718", "entry_level": "bachelor", "ego": "studies-cs/public/results/144831/", "components": [], "languages": {"partially": [], "fully": {"3": {"title": "English", "id": "3", "locale": "en-GB", "item_order": "120", "name": ""}}}, "premiums_out_of_date": ["listed", "sort_regular", "display_regular"], "logo": [], "cpm": "0", "parttime_duration_period": "", "premiums_out_of_range": ["listed", "sort_regular", "display_regular", "out_of_range"], "degree_type": "", "methods": ["face2face"], "degree_formatted": "M.Sc.", "presence": "public", "inquiry_campaigns": [], "venues": {"required": [], "optional": [], "full": {"12499": {"id": "12499", "cities": {"747": {"countries": {"82": {"title": "United States", "id": "82", "item_order": "120", "virtual_path": "united-states.html", "name": "United States"}}, "item_order": "120", "areas": {"3627": {"countries": {"82": {"item_order": "120", "virtual_path": "united-states.html", "area_presence": "yes", "title": "United States", "id": "82", "name": "United States"}}, "title": "Pennsylvania", "id": "3627", "item_order": "120", "name": "Pennsylvania"}}, "title": "Pittsburgh", "id": "747", "name": "Pittsburgh"}}, "item_order": "120", "name": "Pittsburgh Campus"}}}, "rolling": "0", "cae": "", "id": "144831", "ielts": "8", "fce": "", "toefl_paper": "", "start_dates": ["1", "5", "8"], "organisations_lineage": [{"15073": {"item_order": "120", "virtual_path": "duquesne-university.html", "logo": [], "id": "15073", "name": "Duquesne University", "premiums": ["listed", "sort_regular", "display_regular"], "country_id": "82"}}], "degree": "msc", "experience_years": "", "disciplines": {"101": {"title": "Public Administration", "id": "101", "parent_id": "23", "item_order": "120", "name": "Public Administration"}}, "level": "master", "lead_campaigns": [], "fulltime_duration": "24", "premiums": ["listed", "sort_regular", "display_regular"], "commercial_range": ["1", "100"], "name": "Pharmacy Administration"}, "92961": {"commercial_dates": ["", ""], "parttime_duration": "", "item_order": "121", "tuition_fee_types": [{"amount": "47068", "currency": "USD", "unit": "year", "target": "national"}, {"amount": "47068", "currency": "USD", "unit": "year", "target": "international"}], "virtual_path": "public-administration.html", "fulltime_duration_period": "months", "toefl_internet": "100", "title": "", "ects_credits": "", "short_description": "The two-year Master in Public Administration (MPA) Program offered by Harvard Kennedy School equips students who have prior work experience and have taken graduate-level courses with the skills, perspectives, and nuanced understanding they need to be effective leaders in solving public problems.", "entropy": "379544592", "entry_level": "bachelor", "ego": "studies-cs/public/results/92961/", "components": [], "languages": {"partially": [], "fully": {"3": {"title": "English", "id": "3", "locale": "en-GB", "item_order": "120", "name": ""}}}, "premiums_out_of_date": ["listed", "sort_regular", "display_regular"], "logo": [], "cpm": "0", "parttime_duration_period": "", "premiums_out_of_range": ["listed", "sort_regular", "display_regular", "out_of_range"], "degree_type": "", "methods": ["face2face"], "degree_formatted": "Master", "presence": "public", "inquiry_campaigns": [], "venues": {"required": [], "optional": [], "full": {"10840": {"id": "10840", "cities": {"43300": {"countries": {"82": {"title": "United States", "id": "82", "item_order": "120", "virtual_path": "united-states.html", "name": "United States"}}, "item_order": "120", "areas": {"3626": {"countries": {"82": {"item_order": "120", "virtual_path": "united-states.html", "area_presence": "yes", "title": "United States", "id": "82", "name": "United States"}}, "title": "Massachusetts", "id": "3626", "item_order": "120", "name": "Massachusetts"}}, "title": "Cambridge", "id": "43300", "name": "Cambridge"}}, "item_order": "120", "name": "Cambridge Campus"}}}, "rolling": "0", "cae": "", "id": "92961", "ielts": "7", "fce": "", "toefl_paper": "600", "start_dates": [], "organisations_lineage": [{"13454": {"item_order": "120", "virtual_path": "harvard-kennedy-school.html", "logo": {"22800": {"item_order": "120", "imgix": "//storage-prtl-co.imgix.net/mp/772a086d.jpg", "file": "https://storage.prtl.co/mp/772a086d.jpg", "id": "22800", "name": "MPAID_15HKSlogo_StudyPortals_2lineA.jpg", "url": "https://storage.prtl.co/mp/772a086d.jpg"}}, "id": "13454", "name": "Harvard Kennedy School", "premiums": ["listed", "hide_banners", "markup", "links_website", "links_social", "links_rss", "logo", "sort_high", "display_premium", "inquiries", "gallery", "spotlight", "contact_form"], "country_id": "82"}}], "degree": "", "experience_years": "3", "disciplines": {"101": {"title": "Public Administration", "id": "101", "parent_id": "23", "item_order": "120", "name": "Public Administration"}}, "level": "master", "lead_campaigns": [], "fulltime_duration": "24", "premiums": ["listed", "sort_regular", "display_regular"], "commercial_range": ["1", "100"], "name": "Public Administration"}, "138490": {"commercial_dates": ["", ""], "parttime_duration": "", "item_order": "120", "tuition_fee_types": [{"amount": "43034", "currency": "USD", "unit": "year", "target": "national"}, {"amount": "62093", "currency": "USD", "unit": "year", "target": "international"}], "virtual_path": "public-administration.html", "fulltime_duration_period": "months", "toefl_internet": "61", "title": "", "ects_credits": "", "short_description": "The McGeorge School of Law Master of Public Administration (MPA) prepares professionals for successful careers in management and leadership positions and as advocates for change in making and implementing public policies.", "entropy": "373247478", "entry_level": "bachelor", "ego": "studies-cs/public/results/138490/", "components": [], "languages": {"partially": [], "fully": {"3": {"title": "English", "id": "3", "locale": "en-GB", "item_order": "120", "name": ""}}}, "premiums_out_of_date": ["listed", "sort_regular", "display_regular"], "logo": [], "cpm": "0", "parttime_duration_period": "", "premiums_out_of_range": ["listed", "sort_regular", "display_regular", "out_of_range"], "degree_type": "", "methods": ["face2face"], "degree_formatted": "Master", "presence": "public", "inquiry_campaigns": [], "venues": {"required": [], "optional": [], "full": {"12196": {"id": "12196", "cities": {"41184": {"countries": {"82": {"title": "United States", "id": "82", "item_order": "120", "virtual_path": "united-states.html", "name": "United States"}}, "item_order": "120", "areas": {"3585": {"countries": {"82": {"item_order": "120", "virtual_path": "united-states.html", "area_presence": "yes", "title": "United States", "id": "82", "name": "United States"}}, "title": "Maryland", "id": "3585", "item_order": "120", "name": "Maryland"}}, "title": "California", "id": "41184", "name": "California"}}, "item_order": "120", "name": "Stockton Campus"}}}, "rolling": "0", "cae": "", "id": "138490", "ielts": "5", "fce": "", "toefl_paper": "500", "start_dates": [], "organisations_lineage": [{"14728": {"item_order": "120", "virtual_path": "university-of-the-pacific.html", "logo": [], "id": "14728", "name": "University of the Pacific", "premiums": ["listed", "sort_regular", "display_regular"], "country_id": "82"}}], "degree": "", "experience_years": "", "disciplines": {"101": {"title": "Public Administration", "id": "101", "parent_id": "23", "item_order": "120", "name": "Public Administration"}}, "level": "master", "lead_campaigns": [], "fulltime_duration": "24", "premiums": ["listed", "sort_regular", "display_regular"], "commercial_range": ["1", "100"], "name": "Public Administration"}, "51305": {"commercial_dates": ["", ""], "parttime_duration": "36", "item_order": "128", "tuition_fee_types": [{"amount": "16500", "currency": "GBP", "unit": "full", "target": "international"}, {"amount": "16500", "currency": "GBP", "unit": "full", "target": "eea"}], "virtual_path": "public-administration.html", "fulltime_duration_period": "months", "toefl_internet": "90", "title": "", "ects_credits": "", "short_description": "The Master of Public Administration (MPA) offered by The University of Exeter s designed to help you meet the challenge of shaping and delivering effective public services. The Exeter MPA takes an international perspective to equip you with the skills and understanding you need to operate effectively in an increasingly global and constantly changing environment.", "entropy": "410117842", "entry_level": "bachelor", "ego": "studies-cs/public/results/51305/", "components": [], "languages": {"partially": [], "fully": {"3": {"title": "English", "id": "3", "locale": "en-GB", "item_order": "120", "name": ""}}}, "premiums_out_of_date": ["listed", "sort_regular", "display_regular"], "logo": [], "cpm": "0", "parttime_duration_period": "months", "premiums_out_of_range": ["listed", "sort_regular", "display_regular", "out_of_range"], "degree_type": "", "methods": ["face2face"], "degree_formatted": "Master", "presence": "public", "inquiry_campaigns": [], "venues": {"required": [], "optional": [], "full": {"5885": {"id": "5885", "cities": {"199": {"countries": {"30": {"title": "United Kingdom", "id": "30", "item_order": "120", "virtual_path": "united-kingdom.html", "name": "United Kingdom"}}, "item_order": "120", "areas": {"996": {"countries": {"30": {"item_order": "120", "virtual_path": "united-kingdom.html", "area_presence": "yes", "title": "United Kingdom", "id": "30", "name": "United Kingdom"}}, "title": "England", "id": "996", "item_order": "120", "name": "England"}}, "title": "Exeter", "id": "199", "name": "Exeter"}}, "item_order": "120", "name": "Exeter Campus"}}}, "rolling": "0", "cae": "", "id": "51305", "ielts": "6.5", "fce": "", "toefl_paper": "", "start_dates": ["9"], "organisations_lineage": [{"4219": {"item_order": "120", "virtual_path": "college-of-social-sciences-and-international-studies.html", "logo": [], "id": "4219", "name": "College of Social Sciences and International Studies", "premiums": ["listed", "sort_regular", "display_regular"], "country_id": "30"}, "302": {"item_order": "121", "virtual_path": "the-university-of-exeter.html", "logo": {"47796": {"item_order": "120", "imgix": "//storage-prtl-co.imgix.net/mp/d0cafa52.png", "file": "https://storage.prtl.co/mp/d0cafa52.png", "id": "47796", "name": "Exeter logo.png", "url": "https://storage.prtl.co/mp/d0cafa52.png"}}, "id": "302", "name": "The University of Exeter", "premiums": ["listed", "sort_regular", "display_regular"], "country_id": "30"}}], "degree": "", "experience_years": "", "disciplines": {"101": {"title": "Public Administration", "id": "101", "parent_id": "23", "item_order": "120", "name": "Public Administration"}}, "level": "master", "lead_campaigns": [], "fulltime_duration": "12", "premiums": ["listed", "sort_regular", "display_regular"], "commercial_range": ["1", "100"], "name": "Public Administration (MPA)"}, "130069": {"commercial_dates": ["", ""], "parttime_duration": "72", "item_order": "123", "tuition_fee_types": [{"amount": "1020", "currency": "USD", "unit": "credit", "target": "national"}, {"amount": "1020", "currency": "USD", "unit": "credit", "target": "international"}, {"amount": "283", "currency": "USD", "unit": "credit", "target": "local"}], "virtual_path": "business-administrationpublic-administration.html", "fulltime_duration_period": "months", "toefl_internet": "80", "title": "Business Administration/Public Administration", "ects_credits": "", "short_description": "The Master of Business Administration/Master of Public Administration (MBA/MPA) Program is a dual degree offered by the Coles College of Business Administration and the College of Humanities and Social Sciences.", "entropy": "392097210", "entry_level": "bachelor", "ego": "studies-cs/public/results/130069/", "components": [], "languages": {"partially": [], "fully": {"3": {"title": "English", "id": "3", "locale": "en-GB", "item_order": "120", "name": ""}}}, "premiums_out_of_date": ["listed", "sort_regular", "display_regular"], "logo": [], "cpm": "0", "parttime_duration_period": "months", "premiums_out_of_range": ["listed", "sort_regular", "display_regular", "out_of_range"], "degree_type": "", "methods": ["face2face"], "degree_formatted": "Master", "presence": "public", "inquiry_campaigns": [], "venues": {"required": [], "optional": [], "full": {"11716": {"id": "11716", "cities": {"40714": {"countries": {"82": {"title": "United States", "id": "82", "item_order": "120", "virtual_path": "united-states.html", "name": "United States"}}, "item_order": "120", "areas": {"3582": {"countries": {"82": {"item_order": "120", "virtual_path": "united-states.html", "area_presence": "yes", "title": "United States", "id": "82", "name": "United States"}}, "title": "Georgia", "id": "3582", "item_order": "120", "name": "Georgia"}}, "title": "Kennesaw", "id": "40714", "name": "Kennesaw"}}, "item_order": "120", "name": "Kennesaw Campus"}}}, "rolling": "0", "cae": "", "id": "130069", "ielts": "6.5", "fce": "", "toefl_paper": "550", "start_dates": [], "organisations_lineage": [{"14243": {"item_order": "120", "virtual_path": "kennesaw-state-university.html", "logo": [], "id": "14243", "name": "Kennesaw State University", "premiums": ["listed", "sort_regular", "display_regular"], "country_id": "82"}}], "degree": "", "experience_years": "", "disciplines": {"45": {"title": "Business Administration", "id": "45", "parent_id": "23", "item_order": "120", "name": "Business Administration"}, "101": {"title": "Public Administration", "id": "101", "parent_id": "23", "item_order": "121", "name": "Public Administration"}}, "level": "master", "lead_campaigns": [], "fulltime_duration": "36", "premiums": ["listed", "sort_regular", "display_regular"], "commercial_range": ["1", "100"], "name": "Business Administration/Public Administration"}}