{"66082": {"commercial_dates": ["", ""], "parttime_duration": "", "item_order": "460", "tuition_fee_types": [{"amount": "1443", "currency": "USD", "unit": "credit", "target": "national"}, {"amount": "1443", "currency": "USD", "unit": "credit", "target": "local"}], "virtual_path": "public-administration.html", "fulltime_duration_period": "months", "toefl_internet": "105", "title": "", "ects_credits": "", "short_description": "Maxwell's Department of Public Administration and International Affairs has a global reputation for producing graduates with the fundamental public management and policy analysis skill set required by employers in  public, non-profit, and private sector organizations - both domestic and international.", "entropy": "1954387633", "entry_level": "bachelor", "ego": "studies-cs/public/results/66082/", "components": [], "languages": {"partially": [], "fully": {"3": {"title": "English", "id": "3", "locale": "en-GB", "item_order": "460", "name": ""}}}, "premiums_out_of_date": ["listed", "sort_regular", "display_regular"], "logo": [], "cpm": "0", "parttime_duration_period": "", "premiums_out_of_range": ["listed", "sort_regular", "display_regular", "out_of_range"], "degree_type": "", "methods": ["face2face"], "degree_formatted": "Master", "presence": "public", "inquiry_campaigns": [], "venues": {"required": [], "optional": [], "full": {"9349": {"id": "9349", "cities": {"44479": {"countries": {"82": {"title": "United States", "id": "82", "item_order": "460", "virtual_path": "united-states.html", "name": "United States"}}, "item_order": "460", "areas": {"3605": {"countries": {"82": {"item_order": "460", "virtual_path": "united-states.html", "area_presence": "yes", "title": "United States", "id": "82", "name": "United States"}}, "title": "New York", "id": "3605", "item_order": "460", "name": "New York"}}, "title": "Syracuse", "id": "44479", "name": "Syracuse"}}, "item_order": "460", "name": "Syracuse Campus"}}}, "rolling": "0", "cae": "", "id": "66082", "ielts": "7", "fce": "", "toefl_paper": "", "start_dates": ["7"], "organisations_lineage": [{"12201": {"item_order": "460", "virtual_path": "syracuse-university.html", "logo": {"20831": {"item_order": "460", "imgix": "//storage-prtl-co.imgix.net/mp/34e21bfe.png", "file": "https://storage.prtl.co/mp/34e21bfe.png", "id": "20831", "name": "Syracuse University-01.png", "url": "https://storage.prtl.co/mp/34e21bfe.png"}}, "id": "12201", "name": "Syracuse University", "premiums": ["listed"], "country_id": "82"}}], "degree": "", "experience_years": "", "disciplines": {"101": {"title": "Public Administration", "id": "101", "parent_id": "23", "item_order": "460", "name": "Public Administration"}}, "level": "master", "lead_campaigns": [], "fulltime_duration": "12", "premiums": ["listed", "sort_regular", "display_regular"], "commercial_range": ["1", "100"], "name": "Public Administration"}, "122773": {"commercial_dates": ["", ""], "parttime_duration": "", "item_order": "469", "tuition_fee_types": [{"amount": "13892", "currency": "USD", "unit": "semester", "target": "national"}, {"amount": "17820", "currency": "USD", "unit": "semester", "target": "international"}], "virtual_path": "regional-and-city-planning.html", "fulltime_duration_period": "", "toefl_internet": "79", "title": "", "ects_credits": "", "short_description": "The University of Oklahoma College of Architecture prides itself on providing students with a dynamic professional education in Architecture, Construction Science, Interior Design, Landscape Architecture, Regional and City Planning and Environmental Design through a variety of undergraduate and graduate programs in interdisciplinary and collaborative settings emphasizing excellence in education, research and service to the community.", "entropy": "1837165969", "entry_level": "bachelor", "ego": "studies-cs/public/results/122773/", "components": [], "languages": {"partially": [], "fully": {"3": {"title": "English", "id": "3", "locale": "en-GB", "item_order": "460", "name": ""}}}, "premiums_out_of_date": ["listed", "sort_regular", "display_regular"], "logo": [], "cpm": "0", "parttime_duration_period": "", "premiums_out_of_range": ["listed", "sort_regular", "display_regular", "out_of_range"], "degree_type": "", "methods": ["face2face"], "degree_formatted": "Master", "presence": "public", "inquiry_campaigns": [], "venues": {"required": [], "optional": [], "full": {"9415": {"id": "9415", "cities": {"41926": {"countries": {"82": {"title": "United States", "id": "82", "item_order": "460", "virtual_path": "united-states.html", "name": "United States"}}, "item_order": "460", "areas": {"3589": {"countries": {"82": {"item_order": "460", "virtual_path": "united-states.html", "area_presence": "yes", "title": "United States", "id": "82", "name": "United States"}}, "title": "Oklahoma", "id": "3589", "item_order": "460", "name": "Oklahoma"}}, "title": "Norman", "id": "41926", "name": "Norman"}}, "item_order": "460", "name": "Norman Campus"}}}, "rolling": "0", "cae": "", "id": "122773", "ielts": "6.5", "fce": "", "toefl_paper": "550", "start_dates": ["8"], "organisations_lineage": [{"12292": {"item_order": "460", "virtual_path": "university-of-oklahoma.html", "logo": {"20836": {"item_order": "460", "imgix": "//storage-prtl-co.imgix.net/mp/4b04fdf9.png", "file": "https://storage.prtl.co/mp/4b04fdf9.png", "id": "20836", "name": "oklahoma-01.png", "url": "https://storage.prtl.co/mp/4b04fdf9.png"}}, "id": "12292", "name": "University of Oklahoma", "premiums": ["listed", "sort_regular", "display_regular"], "country_id": "82"}}], "degree": "", "experience_years": "", "disciplines": {"321": {"title": "Real Estate & Property Management", "id": "321", "parent_id": "12", "item_order": "461", "name": "Real Estate & Property Management"}, "101": {"title": "Public Administration", "id": "101", "parent_id": "23", "item_order": "460", "name": "Public Administration"}}, "level": "master", "lead_campaigns": [], "fulltime_duration": "", "premiums": ["listed", "sort_regular", "display_regular"], "commercial_range": ["1", "100"], "name": "Regional and City Planning"}, "62104": {"commercial_dates": ["", ""], "parttime_duration": "", "item_order": "468", "tuition_fee_types": [{"amount": "9360", "currency": "AUD", "unit": "module", "target": "national"}, {"amount": "9360", "currency": "AUD", "unit": "module", "target": "international"}], "virtual_path": "public-policy-and-management.html", "fulltime_duration_period": "months", "toefl_internet": "80", "title": "", "ects_credits": "", "short_description": "The Master of Public Policy and Management (MPPM) equips students with the strategic, analytical and professional skills for a career in the government, non-profit, and private sectors both in Australia and internationally. It provides students with the knowledge and skills to analyse, design and implement policy in complex institutional and regulatory environments.", "entropy": "1944229949", "entry_level": "bachelor", "ego": "studies-cs/public/results/62104/", "components": [], "languages": {"partially": [], "fully": {"3": {"title": "English", "id": "3", "locale": "en-GB", "item_order": "460", "name": ""}}}, "premiums_out_of_date": ["listed", "sort_regular", "display_regular"], "logo": [], "cpm": "0", "parttime_duration_period": "", "premiums_out_of_range": ["listed", "sort_regular", "display_regular", "out_of_range"], "degree_type": "", "methods": ["face2face"], "degree_formatted": "Master", "presence": "public", "inquiry_campaigns": [], "venues": {"required": [], "optional": [], "full": {"9108": {"id": "9108", "cities": {"2867": {"countries": {"202": {"title": "Australia", "id": "202", "item_order": "460", "virtual_path": "australia.html", "name": "Australia"}}, "item_order": "460", "areas": {"137": {"countries": {"202": {"item_order": "460", "virtual_path": "australia.html", "area_presence": "yes", "title": "Australia", "id": "202", "name": "Australia"}}, "title": "Western Australia", "id": "137", "item_order": "460", "name": "Western Australia"}}, "title": "Perth", "id": "2867", "name": "Perth"}}, "item_order": "460", "name": "Perth campus"}}}, "rolling": "0", "cae": "180", "id": "62104", "ielts": "6", "fce": "160", "toefl_paper": "550", "start_dates": [], "organisations_lineage": [{"11977": {"item_order": "460", "virtual_path": "murdoch-university.html", "logo": [], "id": "11977", "name": "Murdoch University", "premiums": ["listed"], "country_id": "202"}}], "degree": "", "experience_years": "", "disciplines": {"89": {"title": "Management, Organisation & Leadership", "id": "89", "parent_id": "23", "item_order": "460", "name": "Management, Organisation & Leadership"}, "101": {"title": "Public Administration", "id": "101", "parent_id": "23", "item_order": "461", "name": "Public Administration"}}, "level": "master", "lead_campaigns": [], "fulltime_duration": "24", "premiums": ["listed", "sort_regular", "display_regular"], "commercial_range": ["1", "100"], "name": "Public Policy and Management"}, "71513": {"commercial_dates": ["", ""], "parttime_duration": "", "item_order": "467", "tuition_fee_types": [{"amount": "870", "currency": "USD", "unit": "credit", "target": "national"}, {"amount": "870", "currency": "USD", "unit": "credit", "target": "international"}], "virtual_path": "mbampa-program.html", "fulltime_duration_period": "", "toefl_internet": "80", "title": "", "ects_credits": "", "short_description": "The M.B.A./M.P.A. dual degree program, University of New Haven is designed for those whose interests or career objectives are focused on both the public and private sectors of the economy. The program broadly stresses the use of management skills and analytic techniques applied to business, industrial, governmental, and not-for-profit organizations.", "entropy": "1836674325", "entry_level": "bachelor", "ego": "studies-cs/public/results/71513/", "components": [], "languages": {"partially": [], "fully": {"3": {"title": "English", "id": "3", "locale": "en-GB", "item_order": "460", "name": ""}}}, "premiums_out_of_date": ["listed", "sort_regular", "display_regular"], "logo": [], "cpm": "0", "parttime_duration_period": "", "premiums_out_of_range": ["listed", "sort_regular", "display_regular", "out_of_range"], "degree_type": "", "methods": ["face2face"], "degree_formatted": "M.B.A.", "presence": "public", "inquiry_campaigns": [], "venues": {"required": [], "optional": [], "full": {"10094": {"id": "10094", "cities": {"42788": {"countries": {"82": {"title": "United States", "id": "82", "item_order": "460", "virtual_path": "united-states.html", "name": "United States"}}, "item_order": "460", "areas": {"3595": {"countries": {"82": {"item_order": "460", "virtual_path": "united-states.html", "area_presence": "yes", "title": "United States", "id": "82", "name": "United States"}}, "title": "Connecticut", "id": "3595", "item_order": "460", "name": "Connecticut"}}, "title": "New Haven", "id": "42788", "name": "New Haven"}}, "item_order": "460", "name": "West Haven Campus"}}}, "rolling": "0", "cae": "", "id": "71513", "ielts": "6.5", "fce": "", "toefl_paper": "", "start_dates": ["rolling"], "organisations_lineage": [{"12845": {"item_order": "460", "virtual_path": "university-of-new-haven.html", "logo": [], "id": "12845", "name": "University of New Haven", "premiums": ["listed", "sort_regular", "display_regular"], "country_id": "82"}}], "degree": "mba", "experience_years": "", "disciplines": {"45": {"title": "Business Administration", "id": "45", "parent_id": "23", "item_order": "460", "name": "Business Administration"}, "101": {"title": "Public Administration", "id": "101", "parent_id": "23", "item_order": "461", "name": "Public Administration"}}, "level": "master", "lead_campaigns": [], "fulltime_duration": "", "premiums": ["listed", "sort_regular", "display_regular"], "commercial_range": ["1", "100"], "name": "MBA/MPA Program"}, "63881": {"commercial_dates": ["", ""], "parttime_duration": "", "item_order": "465", "tuition_fee_types": [{"amount": "17814", "currency": "USD", "unit": "semester", "target": "international"}, {"amount": "17814", "currency": "USD", "unit": "semester", "target": "national"}], "virtual_path": "public-administration.html", "fulltime_duration_period": "months", "toefl_internet": "100", "title": "", "ects_credits": "", "short_description": "The Fels Master of Public Administration (MPA) offers a broad-based education that prepares students for leadership roles in government agencies, nonprofit organizations, and private firms engaging in public sector work. If you are committed to public service, the Fels MPA program will help you acquire the skills and knowledge needed to be successful throughout your career.", "entropy": "1945863311", "entry_level": "bachelor", "ego": "studies-cs/public/results/63881/", "components": [], "languages": {"partially": [], "fully": {"3": {"title": "English", "id": "3", "locale": "en-GB", "item_order": "460", "name": ""}}}, "premiums_out_of_date": ["listed", "sort_regular", "display_regular"], "logo": [], "cpm": "0", "parttime_duration_period": "", "premiums_out_of_range": ["listed", "sort_regular", "display_regular", "out_of_range"], "degree_type": "", "methods": ["face2face"], "degree_formatted": "Master", "presence": "public", "inquiry_campaigns": [], "venues": {"required": [], "optional": [], "full": {"8754": {"id": "8754", "cities": {"41979": {"countries": {"82": {"title": "United States", "id": "82", "item_order": "460", "virtual_path": "united-states.html", "name": "United States"}}, "item_order": "460", "areas": {"3627": {"countries": {"82": {"item_order": "460", "virtual_path": "united-states.html", "area_presence": "yes", "title": "United States", "id": "82", "name": "United States"}}, "title": "Pennsylvania", "id": "3627", "item_order": "460", "name": "Pennsylvania"}}, "title": "Philadelphia", "id": "41979", "name": "Philadelphia"}}, "item_order": "460", "name": "Philadelphia Campus"}}}, "rolling": "0", "cae": "", "id": "63881", "ielts": "7.5", "fce": "", "toefl_paper": "600", "start_dates": [], "organisations_lineage": [{"11746": {"item_order": "460", "virtual_path": "university-of-pennsylvania.html", "logo": {"11532": {"item_order": "460", "imgix": "//storage-prtl-co.imgix.net/mp/b9b08493.jpg", "file": "https://storage.prtl.co/mp/b9b08493.jpg", "id": "11532", "name": "logo-print.jpg", "url": "https://storage.prtl.co/mp/b9b08493.jpg"}}, "id": "11746", "name": "University of Pennsylvania", "premiums": ["listed", "sort_regular", "display_regular"], "country_id": "82"}}], "degree": "", "experience_years": "", "disciplines": {"101": {"title": "Public Administration", "id": "101", "parent_id": "23", "item_order": "460", "name": "Public Administration"}}, "level": "master", "lead_campaigns": [], "fulltime_duration": "18", "premiums": ["listed", "sort_regular", "display_regular"], "commercial_range": ["1", "100"], "name": "Public Administration"}, "26013": {"commercial_dates": ["", ""], "parttime_duration": "", "item_order": "464", "tuition_fee_types": [{"amount": "2766", "currency": "EUR", "unit": "year", "target": "eea"}, {"amount": "4500", "currency": "EUR", "unit": "year", "target": "international"}], "virtual_path": "public-administration.html", "fulltime_duration_period": "months", "toefl_internet": "", "title": "Public Administration", "ects_credits": "60", "short_description": "Develop the necessary knowledge and skills with a multidisciplinary outlook which will allow you to work as a professional or specialise in research in the field of public administration.", "entropy": "1949466473", "entry_level": "bachelor", "ego": "studies-cs/public/results/26013/", "components": [], "languages": {"partially": {"30": {"title": "Catalan", "id": "30", "locale": "ca-CA", "item_order": "462", "name": ""}, "6": {"title": "Spanish", "id": "6", "locale": "es-ES", "item_order": "461", "name": ""}, "3": {"title": "English", "id": "3", "locale": "en-GB", "item_order": "460", "name": ""}}, "fully": []}, "premiums_out_of_date": ["listed", "sort_regular", "display_regular"], "logo": [], "cpm": "0", "parttime_duration_period": "", "premiums_out_of_range": ["listed", "sort_regular", "display_regular", "out_of_range"], "degree_type": "", "methods": ["face2face"], "degree_formatted": "M.A.", "presence": "public", "inquiry_campaigns": [], "venues": {"required": [], "optional": [], "full": {"5540": {"id": "5540", "cities": {"34": {"countries": {"24": {"title": "Spain", "id": "24", "item_order": "460", "virtual_path": "spain.html", "name": "Spain"}}, "item_order": "460", "areas": {"927": {"countries": {"24": {"item_order": "460", "virtual_path": "spain.html", "area_presence": "no", "title": "Spain", "id": "24", "name": "Spain"}}, "title": "Catalonia", "id": "927", "item_order": "460", "name": "Catalonia"}}, "title": "Barcelona", "id": "34", "name": "Barcelona"}}, "item_order": "460", "name": "Barcelona Campus"}}}, "rolling": "0", "cae": "", "id": "26013", "ielts": "5", "fce": "", "toefl_paper": "", "start_dates": ["10"], "organisations_lineage": [{"6388": {"item_order": "460", "virtual_path": "political-sciences-society-and-culture.html", "logo": [], "id": "6388", "name": "Political Sciences, Society and Culture", "premiums": ["listed", "sort_regular", "display_regular"], "country_id": "24"}, "42": {"item_order": "461", "virtual_path": "universitat-autnoma-de-barcelona.html", "logo": {"47569": {"item_order": "460", "imgix": "//storage-prtl-co.imgix.net/endor/organisations/42/logos/1496072309_logo.jpg", "file": "//storage.prtl.co/endor/organisations/42/logos/1496072309_logo.jpg", "id": "47569", "name": "Endor", "url": "//storage.prtl.co/endor/organisations/42/logos/1496072309_logo.jpg"}}, "id": "42", "name": "Universitat Aut\u00f2noma de Barcelona", "premiums": ["listed", "sort_regular", "display_regular"], "country_id": "24"}}], "degree": "ma", "experience_years": "", "disciplines": {"101": {"title": "Public Administration", "id": "101", "parent_id": "23", "item_order": "460", "name": "Public Administration"}}, "level": "master", "lead_campaigns": [], "fulltime_duration": "12", "premiums": ["listed", "sort_regular", "display_regular"], "commercial_range": ["1", "100"], "name": "Public Administration"}, "39948": {"commercial_dates": ["", ""], "parttime_duration": "", "item_order": "463", "tuition_fee_types": [{"amount": "2006", "currency": "EUR", "unit": "year", "target": "eea"}, {"amount": "16600", "currency": "EUR", "unit": "year", "target": "international"}], "virtual_path": "public-administration-economics-and-governance.html", "fulltime_duration_period": "months", "toefl_internet": "100", "title": "Public Administration - Economics and Governance", "ects_credits": "60", "short_description": "Solving societal problems often requires a solid multidisciplinary preparation. The Economics and Governance specialisation, offered jointly by the Department of Economics and the Institute of Public Administration, combines insights from the two disciplines.", "entropy": "1831412309", "entry_level": "bachelor", "ego": "studies-cs/public/results/39948/", "components": [], "languages": {"partially": [], "fully": {"3": {"title": "English", "id": "3", "locale": "en-GB", "item_order": "460", "name": ""}}}, "premiums_out_of_date": ["listed", "sort_regular", "display_regular"], "logo": [], "cpm": "0", "parttime_duration_period": "", "premiums_out_of_range": ["listed", "sort_regular", "display_regular", "out_of_range"], "degree_type": "", "methods": ["face2face"], "degree_formatted": "M.Sc.", "presence": "public", "inquiry_campaigns": [], "venues": {"required": [], "optional": [], "full": {"5178": {"id": "5178", "cities": {"46": {"countries": {"1": {"title": "Netherlands", "id": "1", "item_order": "460", "virtual_path": "netherlands.html", "name": "Netherlands"}}, "item_order": "460", "areas": {"2280": {"countries": {"1": {"item_order": "460", "virtual_path": "netherlands.html", "area_presence": "no", "title": "Netherlands", "id": "1", "name": "Netherlands"}}, "title": "South Holland", "id": "2280", "item_order": "460", "name": "South Holland"}}, "title": "Leiden", "id": "46", "name": "Leiden"}}, "item_order": "460", "name": "Leiden Campus"}}}, "rolling": "0", "cae": "", "id": "39948", "ielts": "6.5", "fce": "", "toefl_paper": "600", "start_dates": ["2", "9"], "organisations_lineage": [{"3195": {"item_order": "460", "virtual_path": "faculty-of-social-and-behavioural-sciences.html", "logo": [], "id": "3195", "name": "Faculty of Social and Behavioural Sciences", "premiums": ["listed", "sort_regular", "display_regular"], "country_id": "1"}, "56": {"item_order": "461", "virtual_path": "leiden-university.html", "logo": {"27249": {"item_order": "460", "imgix": "//storage-prtl-co.imgix.net/mp/839f6d3b.png", "file": "https://storage.prtl.co/mp/839f6d3b.png", "id": "27249", "name": "Leiden logo_resized.png", "url": "https://storage.prtl.co/mp/839f6d3b.png"}}, "id": "56", "name": "Leiden University", "premiums": ["listed", "hide_banners", "markup", "links_website", "links_social", "links_rss", "logo", "sort_high", "display_premium", "inquiries", "gallery", "spotlight", "contact_form"], "country_id": "1"}}], "degree": "msc", "experience_years": "", "disciplines": {"4": {"title": "Economics", "id": "4", "parent_id": "13", "item_order": "460", "name": "Economics"}, "101": {"title": "Public Administration", "id": "101", "parent_id": "23", "item_order": "461", "name": "Public Administration"}}, "level": "master", "lead_campaigns": {"213": {"id": "213", "item_order": "460", "name": "Leiden University - 2015"}}, "fulltime_duration": "12", "premiums": ["listed", "sort_regular", "display_regular"], "commercial_range": ["1", "100"], "name": "Public Administration - Economics and Governance"}, "177697": {"commercial_dates": ["", ""], "parttime_duration": "", "item_order": "461", "tuition_fee_types": [{"amount": "1383", "currency": "USD", "unit": "credit", "target": "national"}, {"amount": "1383", "currency": "USD", "unit": "credit", "target": "international"}], "virtual_path": "public-administration.html", "fulltime_duration_period": "months", "toefl_internet": "100", "title": "Public Administration", "ects_credits": "", "short_description": "Are you ready to start or advance your career in public service? Then you\u2019ve come to the right place. The Sawyer Business School is uniquely positioned beside the Massachusetts State House and just steps away from world-renowned hospitals and health centers, and major nonprofits. We are geographically, historically, and academically the ideal training ground for future public servants.", "entropy": "1954156007", "entry_level": "bachelor", "ego": "studies-cs/public/results/177697/", "components": [], "languages": {"partially": [], "fully": {"3": {"title": "English", "id": "3", "locale": "en-GB", "item_order": "460", "name": ""}}}, "premiums_out_of_date": ["listed", "sort_regular", "display_regular"], "logo": [], "cpm": "0", "parttime_duration_period": "", "premiums_out_of_range": ["listed", "sort_regular", "display_regular", "out_of_range"], "degree_type": "MPA", "methods": ["face2face"], "degree_formatted": "Master", "presence": "public", "inquiry_campaigns": [], "venues": {"required": [], "optional": [], "full": {"9354": {"id": "9354", "cities": {"546": {"countries": {"82": {"title": "United States", "id": "82", "item_order": "460", "virtual_path": "united-states.html", "name": "United States"}}, "item_order": "460", "areas": {"3626": {"countries": {"82": {"item_order": "460", "virtual_path": "united-states.html", "area_presence": "yes", "title": "United States", "id": "82", "name": "United States"}}, "title": "Massachusetts", "id": "3626", "item_order": "460", "name": "Massachusetts"}}, "title": "Boston", "id": "546", "name": "Boston"}}, "item_order": "460", "name": "Boston Campus"}}}, "rolling": "0", "cae": "", "id": "177697", "ielts": "7", "fce": "", "toefl_paper": "", "start_dates": [], "organisations_lineage": [{"12219": {"item_order": "460", "virtual_path": "suffolk-university.html", "logo": [], "id": "12219", "name": "Suffolk University", "premiums": ["listed", "sort_regular", "display_regular"], "country_id": "82"}}], "degree": "", "experience_years": "", "disciplines": {"101": {"title": "Public Administration", "id": "101", "parent_id": "23", "item_order": "460", "name": "Public Administration"}}, "level": "master", "lead_campaigns": [], "fulltime_duration": "24", "premiums": ["listed", "sort_regular", "display_regular"], "commercial_range": ["1", "100"], "name": "Public Administration"}, "131609": {"commercial_dates": ["", ""], "parttime_duration": "", "item_order": "466", "tuition_fee_types": [{"amount": "250", "currency": "USD", "unit": "module", "target": "national"}, {"amount": "697", "currency": "USD", "unit": "module", "target": "international"}], "virtual_path": "public-administration.html", "fulltime_duration_period": "months", "toefl_internet": "79", "title": "Public Administration", "ects_credits": "", "short_description": "The mission of the Master of Public Administration program is to strengthen the public service in a democratic and diverse society by educating students to manage and lead public and nonprofit institutions effectively, ethically and democratically.", "entropy": "1836350213", "entry_level": "bachelor", "ego": "studies-cs/public/results/131609/", "components": [], "languages": {"partially": [], "fully": {"3": {"title": "English", "id": "3", "locale": "en-GB", "item_order": "460", "name": ""}}}, "premiums_out_of_date": ["listed", "sort_regular", "display_regular"], "logo": [], "cpm": "0", "parttime_duration_period": "", "premiums_out_of_range": ["listed", "sort_regular", "display_regular", "out_of_range"], "degree_type": "", "methods": ["face2face"], "degree_formatted": "Master", "presence": "public", "inquiry_campaigns": [], "venues": {"required": [], "optional": [], "full": {"11707": {"id": "11707", "cities": {"43872": {"countries": {"82": {"title": "United States", "id": "82", "item_order": "460", "virtual_path": "united-states.html", "name": "United States"}}, "item_order": "460", "areas": {"3602": {"countries": {"82": {"item_order": "460", "virtual_path": "united-states.html", "area_presence": "yes", "title": "United States", "id": "82", "name": "United States"}}, "title": "Nebraska", "id": "3602", "item_order": "460", "name": "Nebraska"}}, "title": "Omaha", "id": "43872", "name": "Omaha"}}, "item_order": "460", "name": "Omaha Campus"}}}, "rolling": "0", "cae": "", "id": "131609", "ielts": "6.5", "fce": "", "toefl_paper": "550", "start_dates": [], "organisations_lineage": [{"14233": {"item_order": "460", "virtual_path": "university-of-nebraska-omaha.html", "logo": [], "id": "14233", "name": "University of Nebraska Omaha", "premiums": ["listed", "sort_regular", "display_regular"], "country_id": "82"}}], "degree": "", "experience_years": "", "disciplines": {"101": {"title": "Public Administration", "id": "101", "parent_id": "23", "item_order": "460", "name": "Public Administration"}}, "level": "master", "lead_campaigns": [], "fulltime_duration": "24", "premiums": ["listed", "sort_regular", "display_regular"], "commercial_range": ["1", "100"], "name": "Public Administration"}, "185605": {"commercial_dates": ["", ""], "parttime_duration": "", "item_order": "462", "tuition_fee_types": [{"amount": "692", "currency": "USD", "unit": "credit", "target": "national"}, {"amount": "351", "currency": "USD", "unit": "credit", "target": "local"}, {"amount": "692", "currency": "USD", "unit": "credit", "target": "international"}], "virtual_path": "public-administration.html", "fulltime_duration_period": "months", "toefl_internet": "", "title": "Public Administration", "ects_credits": "", "short_description": "The Master in Public Administration (MPA) degree program at the University of Southern Indiana is a course of study aimed to train and prepare students to be future managers, administrators and leaders in the public and non-profit sectors throughout the Evansville area, Southwestern Indiana, and the Tri-State region.\u00a0", "entropy": "1949931153", "entry_level": "bachelor", "ego": "studies-cs/public/results/185605/", "components": [], "languages": {"partially": [], "fully": {"3": {"title": "English", "id": "3", "locale": "en-GB", "item_order": "460", "name": ""}}}, "premiums_out_of_date": ["listed", "sort_regular", "display_regular"], "logo": [], "cpm": "0", "parttime_duration_period": "", "premiums_out_of_range": ["listed", "sort_regular", "display_regular", "out_of_range"], "degree_type": "MPA", "methods": ["face2face"], "degree_formatted": "Master", "presence": "public", "inquiry_campaigns": [], "venues": {"required": [], "optional": [], "full": {"14144": {"id": "14144", "cities": {"45017": {"countries": {"82": {"title": "United States", "id": "82", "item_order": "460", "virtual_path": "united-states.html", "name": "United States"}}, "item_order": "460", "areas": {"3609": {"countries": {"82": {"item_order": "460", "virtual_path": "united-states.html", "area_presence": "yes", "title": "United States", "id": "82", "name": "United States"}}, "title": "Wisconsin", "id": "3609", "item_order": "460", "name": "Wisconsin"}}, "title": "Evansville", "id": "45017", "name": "Evansville"}}, "item_order": "460", "name": "Evansville campus"}}}, "rolling": "0", "cae": "", "id": "185605", "ielts": "", "fce": "", "toefl_paper": "", "start_dates": [], "organisations_lineage": [{"17059": {"item_order": "460", "virtual_path": "university-of-southern-indiana.html", "logo": [], "id": "17059", "name": "University of Southern Indiana", "premiums": ["listed", "sort_regular", "display_regular"], "country_id": "82"}}], "degree": "", "experience_years": "", "disciplines": {"101": {"title": "Public Administration", "id": "101", "parent_id": "23", "item_order": "460", "name": "Public Administration"}}, "level": "master", "lead_campaigns": [], "fulltime_duration": "24", "premiums": ["listed", "sort_regular", "display_regular"], "commercial_range": ["1", "100"], "name": "Public Administration"}}