{"44407": {"toefl_paper": "580", "start_dates": ["1", "8"], "name": "Space Physics - Physics", "parttime_duration_period": "", "commercial_dates": ["", ""], "organisations_lineage": [{"3567": {"id": "3567", "logo": [], "item_order": "480", "country_id": "19", "name": "Faculty of Science and Technology", "premiums": ["listed", "sort_regular", "display_regular"], "virtual_path": "faculty-of-science-and-technology.html"}, "177": {"id": "177", "logo": {"4431": {"id": "4431", "item_order": "480", "file": "https://storage.prtl.co/mp/326dadf3.png", "url": "https://storage.prtl.co/mp/326dadf3.png", "name": "logo_black_from website.png", "imgix": "//storage-prtl-co.imgix.net/mp/326dadf3.png"}}, "item_order": "481", "country_id": "19", "name": "UIT the Arctic University of Norway", "premiums": ["listed", "sort_regular", "display_regular"], "virtual_path": "uit-the-arctic-university-of-norway.html"}}], "methods": ["face2face"], "cpm": "0", "experience_years": "", "lead_campaigns": [], "ects_credits": "120", "rolling": "0", "short_description": "The Space Physics - Physics Master's program offered by UIT the Arctic University of Norway   gives you a broad education in Space and Plasma Physics and teaches how to observe the physical processes in the ionosphere associated with space weather with the EISCAT radars.", "item_order": "483", "components": [], "level": "master", "title": "Space Physics - Physics", "inquiry_campaigns": [], "commercial_range": ["1", "100"], "tuition_fee_types": [{"currency": "EUR", "unit": "year", "amount": "0", "target": "eea"}, {"currency": "EUR", "unit": "year", "amount": "0", "target": "international"}], "entropy": "911315648", "ego": "studies-cs/public/results/44407/", "disciplines": {"82": {"id": "82", "title": "Astronomy & Space Sciences", "name": "Astronomy & Space Sciences", "parent_id": "11", "item_order": "481"}, "38": {"id": "38", "title": "Physics", "name": "Physics", "parent_id": "11", "item_order": "480"}}, "id": "44407", "ielts": "6.5", "fce": "", "logo": [], "fulltime_duration_period": "months", "degree": "msc", "degree_formatted": "M.Sc.", "cae": "", "premiums_out_of_date": ["listed", "sort_regular", "display_regular"], "entry_level": "bachelor", "venues": {"full": {"6066": {"id": "6066", "name": "Troms\u00f8 Campus", "cities": {"128": {"id": "128", "areas": {"2295": {"id": "2295", "title": "Troms", "name": "Troms", "item_order": "480", "countries": {"19": {"id": "19", "item_order": "480", "title": "Norway", "name": "Norway", "area_presence": "no", "virtual_path": "norway.html"}}}}, "item_order": "480", "countries": {"19": {"id": "19", "title": "Norway", "name": "Norway", "item_order": "480", "virtual_path": "norway.html"}}, "title": "Troms\u00f8", "name": "Troms\u00f8"}}, "item_order": "480"}}, "required": [], "optional": []}, "virtual_path": "space-physics-physics.html", "fulltime_duration": "24", "presence": "public", "toefl_internet": "85", "parttime_duration": "", "premiums_out_of_range": ["listed", "sort_regular", "display_regular", "out_of_range"], "degree_type": "", "premiums": ["listed", "sort_regular", "display_regular"], "languages": {"partially": [], "fully": {"3": {"id": "3", "title": "English", "name": "", "item_order": "480", "locale": "en-GB"}}}}, "118693": {"toefl_paper": "", "start_dates": [], "name": "Geophysics", "parttime_duration_period": "", "commercial_dates": ["", ""], "organisations_lineage": [{"11969": {"id": "11969", "logo": [], "item_order": "480", "country_id": "56", "name": "University of Western Ontario", "premiums": ["listed"], "virtual_path": "university-of-western-ontario.html"}}], "methods": ["face2face"], "cpm": "0", "experience_years": "", "lead_campaigns": [], "ects_credits": "", "rolling": "0", "short_description": "The primary function of our M.Sc. program is to prepare young scientists for independent research, through the formulation of a research problem, the collection of data, development of analytical methods, review of literature, to writing of the final thesis.", "item_order": "487", "components": [], "level": "master", "title": "Geophysics", "inquiry_campaigns": [], "commercial_range": ["1", "100"], "tuition_fee_types": [{"currency": "CAD", "unit": "year", "amount": "6915", "target": "national"}, {"currency": "CAD", "unit": "year", "amount": "17501", "target": "international"}], "entropy": "920699662", "ego": "studies-cs/public/results/118693/", "disciplines": {"123": {"id": "123", "title": "Geology", "name": "Geology", "parent_id": "117", "item_order": "481"}, "38": {"id": "38", "title": "Physics", "name": "Physics", "parent_id": "11", "item_order": "480"}}, "id": "118693", "ielts": "6", "fce": "", "logo": [], "fulltime_duration_period": "months", "degree": "msc", "degree_formatted": "M.Sc.", "cae": "", "premiums_out_of_date": ["listed", "sort_regular", "display_regular"], "entry_level": "bachelor", "venues": {"full": {"9100": {"id": "9100", "name": "London campus", "cities": {"764": {"id": "764", "areas": {"477": {"id": "477", "title": "Ontario", "name": "Ontario", "item_order": "480", "countries": {"56": {"id": "56", "item_order": "480", "title": "Canada", "name": "Canada", "area_presence": "no", "virtual_path": "canada.html"}}}}, "item_order": "480", "countries": {"56": {"id": "56", "title": "Canada", "name": "Canada", "item_order": "480", "virtual_path": "canada.html"}}, "title": "London", "name": "London"}}, "item_order": "480"}}, "required": [], "optional": []}, "virtual_path": "geophysics.html", "fulltime_duration": "24", "presence": "public", "toefl_internet": "92", "parttime_duration": "", "premiums_out_of_range": ["listed", "sort_regular", "display_regular", "out_of_range"], "degree_type": "", "premiums": ["listed", "sort_regular", "display_regular"], "languages": {"partially": [], "fully": {"3": {"id": "3", "title": "English", "name": "", "item_order": "480", "locale": "en-GB"}}}}, "120471": {"toefl_paper": "600", "start_dates": ["8"], "name": "Physics", "parttime_duration_period": "", "commercial_dates": ["", ""], "organisations_lineage": [{"12394": {"id": "12394", "logo": {"21003": {"id": "21003", "item_order": "480", "file": "https://storage.prtl.co/mp/264515f4.png", "url": "https://storage.prtl.co/mp/264515f4.png", "name": "smu-01.png", "imgix": "//storage-prtl-co.imgix.net/mp/264515f4.png"}}, "item_order": "480", "country_id": "82", "name": "Southern Methodist University", "premiums": ["listed"], "virtual_path": "southern-methodist-university.html"}}], "methods": ["face2face"], "cpm": "0", "experience_years": "", "lead_campaigns": [], "ects_credits": "", "rolling": "0", "short_description": "SMU Physics is dedicated to excellence in graduate education for small numbers of students with an emphasis on high-energy particle physics and particle astrophysics.", "item_order": "486", "components": [], "level": "master", "title": "Physics", "inquiry_campaigns": [], "commercial_range": ["1", "100"], "tuition_fee_types": [], "entropy": "918519844", "ego": "studies-cs/public/results/120471/", "disciplines": {"38": {"id": "38", "title": "Physics", "name": "Physics", "parent_id": "11", "item_order": "480"}}, "id": "120471", "ielts": "6.5", "fce": "", "logo": [], "fulltime_duration_period": "", "degree": "msc", "degree_formatted": "M.Sc.", "cae": "", "premiums_out_of_date": ["listed", "sort_regular", "display_regular"], "entry_level": "bachelor", "venues": {"full": {"9513": {"id": "9513", "name": "Dallas Campus", "cities": {"46195": {"id": "46195", "areas": {"3619": {"id": "3619", "title": "Oregon", "name": "Oregon", "item_order": "480", "countries": {"82": {"id": "82", "item_order": "480", "title": "United States", "name": "United States", "area_presence": "yes", "virtual_path": "united-states.html"}}}}, "item_order": "480", "countries": {"82": {"id": "82", "title": "United States", "name": "United States", "item_order": "480", "virtual_path": "united-states.html"}}, "title": "Dallas", "name": "Dallas"}}, "item_order": "480"}}, "required": [], "optional": []}, "virtual_path": "physics.html", "fulltime_duration": "", "presence": "public", "toefl_internet": "100", "parttime_duration": "", "premiums_out_of_range": ["listed", "sort_regular", "display_regular", "out_of_range"], "degree_type": "", "premiums": ["listed", "sort_regular", "display_regular"], "languages": {"partially": [], "fully": {"3": {"id": "3", "title": "English", "name": "", "item_order": "480", "locale": "en-GB"}}}}, "175144": {"toefl_paper": "", "start_dates": [], "name": "Adolescent Physics", "parttime_duration_period": "", "commercial_dates": ["", ""], "organisations_lineage": [{"16688": {"id": "16688", "logo": [], "item_order": "480", "country_id": "82", "name": "Queens College", "premiums": ["listed", "sort_regular", "display_regular"], "virtual_path": "queens-college.html"}}], "methods": ["face2face"], "cpm": "0", "experience_years": "", "lead_campaigns": [], "ects_credits": "", "rolling": "0", "short_description": "Responsible preparation for work in secondary school and community settings requires that in addition to meeting the academic standards established by each program, candidates demonstrate appropriate personal characteristics, which would include professional judgment, ethical conduct, and academic integrity.\u00a0", "item_order": "488", "components": [], "level": "master", "title": "Adolescent Physics", "inquiry_campaigns": [], "commercial_range": ["1", "100"], "tuition_fee_types": [{"currency": "USD", "unit": "credit", "amount": "425", "target": "national"}, {"currency": "USD", "unit": "credit", "amount": "780", "target": "international"}], "entropy": "931062762", "ego": "studies-cs/public/results/175144/", "disciplines": {"8": {"id": "8", "title": "Education", "name": "Education", "parent_id": "289", "item_order": "480"}, "38": {"id": "38", "title": "Physics", "name": "Physics", "parent_id": "11", "item_order": "481"}}, "id": "175144", "ielts": "", "fce": "", "logo": [], "fulltime_duration_period": "months", "degree": "ma", "degree_formatted": "M.A.", "cae": "", "premiums_out_of_date": ["listed", "sort_regular", "display_regular"], "entry_level": "bachelor", "venues": {"full": {"13887": {"id": "13887", "name": "New York campus", "cities": {"525": {"id": "525", "areas": {"3605": {"id": "3605", "title": "New York", "name": "New York", "item_order": "480", "countries": {"82": {"id": "82", "item_order": "480", "title": "United States", "name": "United States", "area_presence": "yes", "virtual_path": "united-states.html"}}}}, "item_order": "480", "countries": {"82": {"id": "82", "title": "United States", "name": "United States", "item_order": "480", "virtual_path": "united-states.html"}}, "title": "New York City", "name": "New York City"}}, "item_order": "480"}}, "required": [], "optional": []}, "virtual_path": "adolescent-physics.html", "fulltime_duration": "24", "presence": "public", "toefl_internet": "", "parttime_duration": "", "premiums_out_of_range": ["listed", "sort_regular", "display_regular", "out_of_range"], "degree_type": "", "premiums": ["listed", "sort_regular", "display_regular"], "languages": {"partially": [], "fully": {"3": {"id": "3", "title": "English", "name": "", "item_order": "480", "locale": "en-GB"}}}}, "188279": {"toefl_paper": "", "start_dates": [], "name": "Mathematics and Applied Physics", "parttime_duration_period": "", "commercial_dates": ["", ""], "organisations_lineage": [{"1222": {"id": "1222", "logo": [], "item_order": "480", "country_id": "20", "name": "Rzeszow University of Technology", "premiums": ["listed"], "virtual_path": "rzeszow-university-of-technology.html"}}], "methods": ["face2face"], "cpm": "0", "experience_years": "", "lead_campaigns": [], "ects_credits": "120", "rolling": "0", "short_description": "The Faculty of Mathematics and Applied Physics offers degree at the level of Master of Science (MSc), which requires two years of study including advanced courses and a Master's thesis. All credits cited are according to the European Community Course Credit Transfer System (ECTS).", "item_order": "481", "components": [], "level": "master", "title": "Mathematics and Applied Physics", "inquiry_campaigns": [], "commercial_range": ["1", "100"], "tuition_fee_types": [{"currency": "EUR", "unit": "full", "amount": "6576", "target": "eea"}, {"currency": "EUR", "unit": "full", "amount": "6576", "target": "international"}], "entropy": "904197620", "ego": "studies-cs/public/results/188279/", "disciplines": {"40": {"id": "40", "title": "Mathematics", "name": "Mathematics", "parent_id": "11", "item_order": "481"}, "38": {"id": "38", "title": "Physics", "name": "Physics", "parent_id": "11", "item_order": "480"}}, "id": "188279", "ielts": "", "fce": "", "logo": [], "fulltime_duration_period": "months", "degree": "msc", "degree_formatted": "M.Sc.", "cae": "", "premiums_out_of_date": ["listed", "sort_regular", "display_regular"], "entry_level": "bachelor", "venues": {"full": {"6528": {"id": "6528", "name": "Campus", "cities": {"438": {"id": "438", "areas": {"2447": {"id": "2447", "title": "Subcarpathian Voivodeship", "name": "Subcarpathian Voivodeship", "item_order": "480", "countries": {"20": {"id": "20", "item_order": "480", "title": "Poland", "name": "Poland", "area_presence": "no", "virtual_path": "poland.html"}}}}, "item_order": "480", "countries": {"20": {"id": "20", "title": "Poland", "name": "Poland", "item_order": "480", "virtual_path": "poland.html"}}, "title": "Rzesz\u00f3w", "name": "Rzesz\u00f3w"}}, "item_order": "480"}}, "required": [], "optional": []}, "virtual_path": "mathematics-and-applied-physics.html", "fulltime_duration": "24", "presence": "public", "toefl_internet": "", "parttime_duration": "", "premiums_out_of_range": ["listed", "sort_regular", "display_regular", "out_of_range"], "degree_type": "", "premiums": ["listed", "sort_regular", "display_regular"], "languages": {"partially": [], "fully": {"3": {"id": "3", "title": "English", "name": "", "item_order": "480", "locale": "en-GB"}}}}, "111701": {"toefl_paper": "", "start_dates": ["9"], "name": "Biophysics", "parttime_duration_period": "", "commercial_dates": ["", ""], "organisations_lineage": [{"11827": {"id": "11827", "logo": {"11457": {"id": "11457", "item_order": "480", "file": "https://storage.prtl.co/mp/305762e2.png", "url": "https://storage.prtl.co/mp/305762e2.png", "name": "umd_logo.png", "imgix": "//storage-prtl-co.imgix.net/mp/305762e2.png"}}, "item_order": "480", "country_id": "82", "name": "University of Maryland", "premiums": ["listed", "sort_regular", "display_regular"], "virtual_path": "university-of-maryland.html"}}], "methods": ["face2face"], "cpm": "0", "experience_years": "", "lead_campaigns": [], "ects_credits": "", "rolling": "0", "short_description": "The Maryland Biophysics Program aims to train graduate students in the use of theoretical, computational, and experimental methods to gain quantitative insights into biological systems.\u00a0", "item_order": "480", "components": [], "level": "master", "title": "Biophysics", "inquiry_campaigns": [], "commercial_range": ["1", "100"], "tuition_fee_types": [{"currency": "USD", "unit": "credit", "amount": "683", "target": "national"}, {"currency": "USD", "unit": "credit", "amount": "1474", "target": "international"}], "entropy": "901769652", "ego": "studies-cs/public/results/111701/", "disciplines": {"81": {"id": "81", "title": "Biology", "name": "Biology", "parent_id": "11", "item_order": "481"}, "38": {"id": "38", "title": "Physics", "name": "Physics", "parent_id": "11", "item_order": "480"}}, "id": "111701", "ielts": "7", "fce": "", "logo": [], "fulltime_duration_period": "", "degree": "", "degree_formatted": "Master", "cae": "", "premiums_out_of_date": ["listed", "sort_regular", "display_regular"], "entry_level": "bachelor", "venues": {"full": {"8854": {"id": "8854", "name": "College Park Campus", "cities": {"41202": {"id": "41202", "areas": {"3585": {"id": "3585", "title": "Maryland", "name": "Maryland", "item_order": "480", "countries": {"82": {"id": "82", "item_order": "480", "title": "United States", "name": "United States", "area_presence": "yes", "virtual_path": "united-states.html"}}}}, "item_order": "480", "countries": {"82": {"id": "82", "title": "United States", "name": "United States", "item_order": "480", "virtual_path": "united-states.html"}}, "title": "College Park", "name": "College Park"}}, "item_order": "480"}}, "required": [], "optional": []}, "virtual_path": "biophysics.html", "fulltime_duration": "", "presence": "public", "toefl_internet": "100", "parttime_duration": "", "premiums_out_of_range": ["listed", "sort_regular", "display_regular", "out_of_range"], "degree_type": "", "premiums": ["listed", "sort_regular", "display_regular"], "languages": {"partially": [], "fully": {"3": {"id": "3", "title": "English", "name": "", "item_order": "480", "locale": "en-GB"}}}}, "120770": {"toefl_paper": "550", "start_dates": ["9"], "name": "Physics", "parttime_duration_period": "", "commercial_dates": ["", ""], "organisations_lineage": [{"11732": {"id": "11732", "logo": {"19685": {"id": "19685", "item_order": "480", "file": "https://storage.prtl.co/mp/f924ed8f.jpg", "url": "https://storage.prtl.co/mp/f924ed8f.jpg", "name": "download.jpg", "imgix": "//storage-prtl-co.imgix.net/mp/f924ed8f.jpg"}}, "item_order": "480", "country_id": "82", "name": "University of Utah", "premiums": ["listed", "sort_regular", "display_regular"], "virtual_path": "university-of-utah.html"}}], "methods": ["face2face"], "cpm": "0", "experience_years": "", "lead_campaigns": [], "ects_credits": "", "rolling": "0", "short_description": "Approximately 20 students enter the graduate program annually, with an even split between those entering the M.S. and PhD programs. The M.S. degree in the Department of Physics & Astronomy requires a thesis or non-thesis degree and provides comprehensive course and research experience.", "item_order": "484", "components": [], "level": "master", "title": "Physics", "inquiry_campaigns": [], "commercial_range": ["1", "100"], "tuition_fee_types": [{"currency": "USD", "unit": "credit", "amount": "3819", "target": "national"}, {"currency": "USD", "unit": "credit", "amount": "3819", "target": "international"}], "entropy": "912409606", "ego": "studies-cs/public/results/120770/", "disciplines": {"38": {"id": "38", "title": "Physics", "name": "Physics", "parent_id": "11", "item_order": "480"}}, "id": "120770", "ielts": "6.5", "fce": "", "logo": [], "fulltime_duration_period": "months", "degree": "msc", "degree_formatted": "M.Sc.", "cae": "160", "premiums_out_of_date": ["listed", "sort_regular", "display_regular"], "entry_level": "bachelor", "venues": {"full": {"8740": {"id": "8740", "name": "Salt Lake City Campus", "cities": {"46330": {"id": "46330", "areas": {"3614": {"id": "3614", "title": "Utah", "name": "Utah", "item_order": "480", "countries": {"82": {"id": "82", "item_order": "480", "title": "United States", "name": "United States", "area_presence": "yes", "virtual_path": "united-states.html"}}}}, "item_order": "480", "countries": {"82": {"id": "82", "title": "United States", "name": "United States", "item_order": "480", "virtual_path": "united-states.html"}}, "title": "Salt Lake City", "name": "Salt Lake City"}}, "item_order": "480"}}, "required": [], "optional": []}, "virtual_path": "physics.html", "fulltime_duration": "24", "presence": "public", "toefl_internet": "80", "parttime_duration": "", "premiums_out_of_range": ["listed", "sort_regular", "display_regular", "out_of_range"], "degree_type": "", "premiums": ["listed", "sort_regular", "display_regular"], "languages": {"partially": [], "fully": {"3": {"id": "3", "title": "English", "name": "", "item_order": "480", "locale": "en-GB"}}}}, "127341": {"toefl_paper": "550", "start_dates": [], "name": "Applied Physics", "parttime_duration_period": "", "commercial_dates": ["", ""], "organisations_lineage": [{"12266": {"id": "12266", "logo": {"20949": {"id": "20949", "item_order": "480", "file": "https://storage.prtl.co/mp/3231947e.png", "url": "https://storage.prtl.co/mp/3231947e.png", "name": "TTU-01.png", "imgix": "//storage-prtl-co.imgix.net/mp/3231947e.png"}}, "item_order": "480", "country_id": "82", "name": "Texas Tech University", "premiums": ["listed", "sort_regular", "display_regular"], "virtual_path": "texas-tech-university.html"}}], "methods": ["face2face"], "cpm": "0", "experience_years": "", "lead_campaigns": [], "ects_credits": "", "rolling": "0", "short_description": "The Department of Physics at Texas Tech University invites applications for graduate study in Physics, leading to the masters or doctoral degree in Physics or Applied Physics.", "item_order": "482", "components": [], "level": "master", "title": "Applied Physics", "inquiry_campaigns": [], "commercial_range": ["1", "100"], "tuition_fee_types": [{"currency": "USD", "unit": "module", "amount": "16746", "target": "national"}, {"currency": "USD", "unit": "module", "amount": "16746", "target": "international"}, {"currency": "USD", "unit": "module", "amount": "8486", "target": "local"}], "entropy": "905318164", "ego": "studies-cs/public/results/127341/", "disciplines": {"38": {"id": "38", "title": "Physics", "name": "Physics", "parent_id": "11", "item_order": "480"}}, "id": "127341", "ielts": "6.5", "fce": "", "logo": [], "fulltime_duration_period": "months", "degree": "msc", "degree_formatted": "M.Sc.", "cae": "", "premiums_out_of_date": ["listed", "sort_regular", "display_regular"], "entry_level": "bachelor", "venues": {"full": {"11650": {"id": "11650", "name": "Lubbock Campus", "cities": {"46027": {"id": "46027", "areas": {"3592": {"id": "3592", "title": "Texas", "name": "Texas", "item_order": "480", "countries": {"82": {"id": "82", "item_order": "480", "title": "United States", "name": "United States", "area_presence": "yes", "virtual_path": "united-states.html"}}}}, "item_order": "480", "countries": {"82": {"id": "82", "title": "United States", "name": "United States", "item_order": "480", "virtual_path": "united-states.html"}}, "title": "Lubbock", "name": "Lubbock"}}, "item_order": "480"}}, "required": [], "optional": []}, "virtual_path": "applied-physics.html", "fulltime_duration": "24", "presence": "public", "toefl_internet": "79", "parttime_duration": "", "premiums_out_of_range": ["listed", "sort_regular", "display_regular", "out_of_range"], "degree_type": "", "premiums": ["listed", "sort_regular", "display_regular"], "languages": {"partially": [], "fully": {"3": {"id": "3", "title": "English", "name": "", "item_order": "480", "locale": "en-GB"}}}}, "117317": {"toefl_paper": "", "start_dates": ["8"], "name": "Medical Physics", "parttime_duration_period": "", "commercial_dates": ["", ""], "organisations_lineage": [{"12172": {"id": "12172", "logo": {"19654": {"id": "19654", "item_order": "480", "file": "https://storage.prtl.co/mp/572bb56b.jpg", "url": "https://storage.prtl.co/mp/572bb56b.jpg", "name": "VCU_3CSeal.jpg", "imgix": "//storage-prtl-co.imgix.net/mp/572bb56b.jpg"}}, "item_order": "480", "country_id": "82", "name": "Virginia Commonwealth University", "premiums": ["listed", "sort_regular", "display_regular"], "virtual_path": "virginia-commonwealth-university.html"}}], "methods": ["face2face"], "cpm": "0", "experience_years": "", "lead_campaigns": [], "ects_credits": "", "rolling": "0", "short_description": "The Master of Science in Medical Physics offers students course work and practical clinical training in physics as it is applied to the diagnosis and treatment of human diseases. The mission of the master\u2019s program is to serve the commonwealth of Virginia and the nation by helping to meet the demand for competent medical physicists in the health care delivery setting.", "item_order": "485", "components": [], "level": "master", "title": "", "inquiry_campaigns": [], "commercial_range": ["1", "100"], "tuition_fee_types": [], "entropy": "914385990", "ego": "studies-cs/public/results/117317/", "disciplines": {"92": {"id": "92", "title": "Human Medicine", "name": "Human Medicine", "parent_id": "10", "item_order": "481"}, "38": {"id": "38", "title": "Physics", "name": "Physics", "parent_id": "11", "item_order": "480"}}, "id": "117317", "ielts": "", "fce": "", "logo": [], "fulltime_duration_period": "", "degree": "msc", "degree_formatted": "M.Sc.", "cae": "", "premiums_out_of_date": ["listed", "sort_regular", "display_regular"], "entry_level": "bachelor", "venues": {"full": {"9329": {"id": "9329", "name": "Richmond Campus", "cities": {"43833": {"id": "43833", "areas": {"3601": {"id": "3601", "title": "Minnesota", "name": "Minnesota", "item_order": "480", "countries": {"82": {"id": "82", "item_order": "480", "title": "United States", "name": "United States", "area_presence": "yes", "virtual_path": "united-states.html"}}}}, "item_order": "480", "countries": {"82": {"id": "82", "title": "United States", "name": "United States", "item_order": "480", "virtual_path": "united-states.html"}}, "title": "Fairfax", "name": "Virginia"}}, "item_order": "480"}}, "required": [], "optional": []}, "virtual_path": "medical-physics.html", "fulltime_duration": "", "presence": "public", "toefl_internet": "", "parttime_duration": "", "premiums_out_of_range": ["listed", "sort_regular", "display_regular", "out_of_range"], "degree_type": "", "premiums": ["listed", "sort_regular", "display_regular"], "languages": {"partially": [], "fully": {"3": {"id": "3", "title": "English", "name": "", "item_order": "480", "locale": "en-GB"}}}}, "113071": {"toefl_paper": "", "start_dates": ["9"], "name": "Photonics", "parttime_duration_period": "", "commercial_dates": ["", ""], "organisations_lineage": [{"1014": {"id": "1014", "logo": {"19750": {"id": "19750", "item_order": "480", "file": "https://storage.prtl.co/mp/4a467b37.png", "url": "https://storage.prtl.co/mp/4a467b37.png", "name": "BU-logo.png", "imgix": "//storage-prtl-co.imgix.net/mp/4a467b37.png"}}, "item_order": "480", "country_id": "82", "name": "Boston University", "premiums": ["listed", "sort_regular", "display_regular"], "virtual_path": "boston-university.html"}}], "methods": ["face2face"], "cpm": "0", "experience_years": "", "lead_campaigns": [], "ects_credits": "", "rolling": "0", "short_description": "The Master of Engineering (MEng) program in Photonics is designed to prepare students for technically demanding careers in industry as well as for post-master\u2019s graduate studies in photonics or related fields.\u00a0", "item_order": "489", "components": [], "level": "master", "title": "Photonics", "inquiry_campaigns": [], "commercial_range": ["1", "100"], "tuition_fee_types": [{"currency": "USD", "unit": "year", "amount": "49176", "target": "national"}, {"currency": "USD", "unit": "year", "amount": "49176", "target": "international"}], "entropy": "933769078", "ego": "studies-cs/public/results/113071/", "disciplines": {"38": {"id": "38", "title": "Physics", "name": "Physics", "parent_id": "11", "item_order": "480"}}, "id": "113071", "ielts": "7", "fce": "", "logo": [], "fulltime_duration_period": "", "degree": "meng", "degree_formatted": "M.Eng.", "cae": "", "premiums_out_of_date": ["listed", "sort_regular", "display_regular"], "entry_level": "bachelor", "venues": {"full": {"8014": {"id": "8014", "name": "Boston Campus", "cities": {"546": {"id": "546", "areas": {"3626": {"id": "3626", "title": "Massachusetts", "name": "Massachusetts", "item_order": "480", "countries": {"82": {"id": "82", "item_order": "480", "title": "United States", "name": "United States", "area_presence": "yes", "virtual_path": "united-states.html"}}}}, "item_order": "480", "countries": {"82": {"id": "82", "title": "United States", "name": "United States", "item_order": "480", "virtual_path": "united-states.html"}}, "title": "Boston", "name": "Boston"}}, "item_order": "480"}}, "required": [], "optional": []}, "virtual_path": "photonics.html", "fulltime_duration": "", "presence": "public", "toefl_internet": "90", "parttime_duration": "", "premiums_out_of_range": ["listed", "sort_regular", "display_regular", "out_of_range"], "degree_type": "", "premiums": ["listed", "sort_regular", "display_regular"], "languages": {"partially": [], "fully": {"3": {"id": "3", "title": "English", "name": "", "item_order": "480", "locale": "en-GB"}}}}}